TractSeg-2.9.data/scripts/ExpRunner
TractSeg-2.9.data/scripts/Tracking
TractSeg-2.9.data/scripts/TractSeg
TractSeg-2.9.data/scripts/Tractometry
TractSeg-2.9.data/scripts/calc_FA
TractSeg-2.9.data/scripts/download_all_pretrained_weights
TractSeg-2.9.data/scripts/flip_peaks
TractSeg-2.9.data/scripts/get_image_spacing
TractSeg-2.9.data/scripts/plot_tractometry_results
TractSeg-2.9.data/scripts/remove_negative_values
TractSeg-2.9.data/scripts/rotate_bvecs
tests/__init__.py
tests/test_end_to_end.py
tests/test_functions.py
tractseg/__init__.py
tractseg/python_api.py
tractseg/data/DLDABG_standalone.py
tractseg/data/__init__.py
tractseg/data/check_data.py
tractseg/data/custom_transformations.py
tractseg/data/data_loader_inference.py
tractseg/data/data_loader_precomputed.py
tractseg/data/data_loader_training.py
tractseg/data/data_loader_training_3D.py
tractseg/data/dataset_specific_utils.py
tractseg/data/preprocessing.py
tractseg/data/spatial_transform_custom.py
tractseg/data/spatial_transform_peaks.py
tractseg/data/subjects.py
tractseg/experiments/__init__.py
tractseg/experiments/base.py
tractseg/experiments/dm_reg.py
tractseg/experiments/dm_reg_lowres.py
tractseg/experiments/endings_seg.py
tractseg/experiments/endings_seg_lowres.py
tractseg/experiments/peak_reg.py
tractseg/experiments/peak_reg_angle.py
tractseg/experiments/peak_reg_lowres.py
tractseg/experiments/tract_seg.py
tractseg/experiments/tract_seg_lowres.py
tractseg/experiments/base_legacy/__init__.py
tractseg/experiments/base_legacy/dm_reg_legacy.py
tractseg/experiments/base_legacy/dm_reg_lowres_legacy.py
tractseg/experiments/base_legacy/endings_seg_legacy.py
tractseg/experiments/base_legacy/endings_seg_lowres_legacy.py
tractseg/experiments/base_legacy/peak_reg_legacy.py
tractseg/experiments/base_legacy/peak_reg_lowres_legacy.py
tractseg/experiments/base_legacy/tract_seg_legacy.py
tractseg/experiments/base_legacy/tract_seg_lowres_legacy.py
tractseg/experiments/pretrained_models/DmReg.py
TractSeg-2.9.dist-info/LICENSE
TractSeg-2.9.dist-info/METADATA
TractSeg-2.9.dist-info/WHEEL
TractSeg-2.9.dist-info/top_level.txt
TractSeg-2.9.dist-info/RECORD
