Metadata-Version: 2.1
Name: TractSeg
Version: 2.9
Summary: Fast and accurate segmentation of white matter bundles
Home-page: https://github.com/MIC-DKFZ/TractSeg/
Author: Jakob Wasserthal
Author-email: j.wasserthal@dkfz-heidelberg.de
License: Apache 2.0
Platform: UNKNOWN
Classifier: Intended Audience :: Science/Research
Classifier: Programming Language :: Python
Classifier: Topic :: Scientific/Engineering
Classifier: Operating System :: Unix
Classifier: Operating System :: MacOS
Requires-Python: >=3.5
License-File: LICENSE
Requires-Dist: future
Requires-Dist: numpy
Requires-Dist: nibabel (>=2.3.0)
Requires-Dist: matplotlib
Requires-Dist: scikit-learn
Requires-Dist: scipy
Requires-Dist: tqdm
Requires-Dist: six
Requires-Dist: psutil
Requires-Dist: dipy (>=1.5.0)
Requires-Dist: fury
Requires-Dist: joblib (>=0.13.2)
Requires-Dist: seaborn
Requires-Dist: requests
Requires-Dist: xvfbwrapper
